README.rst
setup.py
mixem/__init__.py
mixem/em.py
mixem/model.py
mixem/progress.py
mixem.egg-info/PKG-INFO
mixem.egg-info/SOURCES.txt
mixem.egg-info/dependency_links.txt
mixem.egg-info/requires.txt
mixem.egg-info/top_level.txt
mixem/distribution/__init__.py
mixem/distribution/distribution.py
mixem/distribution/exponential.py
mixem/distribution/geometric.py
mixem/distribution/normal.py