Metadata-Version: 1.1
Name: mixem
Version: 0.1.3
Summary: Expectation-Maximization (EM) algorithm for fitting mixtures of probability distributions
Home-page: https://github.com/sseemayer/mixem
Author: Stefan Seemayer
Author-email: stefan@seemayer.de
License: MIT
Keywords: numeric em expectation maximization probability statistics distribution
Platform: UNKNOWN
Classifier: Development Status :: 3 - Alpha
Classifier: Operating System :: OS Independent
Classifier: License :: OSI Approved :: MIT License
Classifier: Intended Audience :: Science/Research
Classifier: Intended Audience :: Financial and Insurance Industry
Classifier: Topic :: Scientific/Engineering :: Bio-Informatics
Classifier: Topic :: Scientific/Engineering :: Artificial Intelligence
Classifier: Topic :: Scientific/Engineering :: Mathematics
